passguardian/__init__.py
passguardian/breaches.py
passguardian/evaluator.py
passguardian/generator.py
passguardian-1.0.0.dist-info/METADATA
passguardian-1.0.0.dist-info/WHEEL
passguardian-1.0.0.dist-info/entry_points.txt
passguardian-1.0.0.dist-info/top_level.txt
passguardian-1.0.0.dist-info/RECORD
