Metadata-Version: 2.4
Name: passguardian
Version: 1.0.0
Summary: A smart password strength evaluator and generator with entropy scoring and breach check.
Author-email: Naman Vora <your.email@example.com>
License-Expression: MIT
Requires-Python: >=3.7
Requires-Dist: requests
Requires-Dist: rich
